hw_project_01/__init__.py
hw_project_01-0.1.2.dist-info/METADATA
hw_project_01-0.1.2.dist-info/WHEEL
hw_project_01-0.1.2.dist-info/RECORD
