Metadata-Version: 2.3
Name: hw-project-01
Version: 0.1.2
Summary: 
Author: v.zajczev
Author-email: v.zajczev@globus.ru
Requires-Python: >=3.11
Classifier: Programming Language :: Python :: 3
Classifier: Programming Language :: Python :: 3.11
Classifier: Programming Language :: Python :: 3.12
Classifier: Programming Language :: Python :: 3.13
Requires-Dist: requests (>=2.32.4,<3.0.0)
